subprocess_print_and_capture/LICENSE
subprocess_print_and_capture/README.MD
subprocess_print_and_capture/__init__.py
subprocess_print_and_capture/requirements.txt
subprocess_print_and_capture/thirdparty.json
subprocess_print_and_capture-0.16.dist-info/LICENSE.rst
subprocess_print_and_capture-0.16.dist-info/METADATA
subprocess_print_and_capture-0.16.dist-info/WHEEL
subprocess_print_and_capture-0.16.dist-info/top_level.txt
subprocess_print_and_capture-0.16.dist-info/RECORD
